sharded_queue/__init__.py
sharded_queue/drivers.py
sharded_queue/protocols.py
sharded_queue/settings.py
sharded_queue-0.2.10.dist-info/METADATA
sharded_queue-0.2.10.dist-info/WHEEL
sharded_queue-0.2.10.dist-info/licenses/LICENSE
sharded_queue-0.2.10.dist-info/RECORD
