Metadata-Version: 2.3
Name: sharded-queue
Version: 0.2.10
Summary: Sharded queue implementation
Project-URL: Homepage, https://github.com/basis-company/sharded-queue.py
Project-URL: Bug Tracker, https://github.com/basis-company/sharded-queue.py/issues
Author-email: Dmitry Krokhin <nekufa@gmail.com>
License-File: LICENSE
Classifier: License :: OSI Approved :: MIT License
Classifier: Operating System :: OS Independent
Classifier: Programming Language :: Python :: 3
Requires-Python: >=3.11
